{
    "_type": "export",
    "__export_format": 4,
    "__export_date": "2022-08-20T15:59:31.709Z",
    "__export_source": "insomnia.desktop.app:v2022.5.0",
    "resources": [
        {
            "_id": "req_8c5e9d04daa348478540f1d1c6dfc79b",
            "parentId": "wrk_a2af50c119e7496c87eff35e49c5520b",
            "modified": 1661008801251,
            "created": 1661005354878,
            "url": "http://localhost:3001/",
            "name": "Root",
            "description": "",
            "method": "GET",
            "body": {},
            "parameters": [],
            "headers": [],
            "authentication": {},
            "metaSortKey": -1661008774676,
            "isPrivate": false,
            "settingStoreCookies": true,
            "settingSendCookies": true,
            "settingDisableRenderRequestBody": false,
            "settingEncodeUrl": true,
            "settingRebuildPath": true,
            "settingFollowRedirects": "global",
            "_type": "request"
        },
        {
            "_id": "wrk_a2af50c119e7496c87eff35e49c5520b",
            "parentId": null,
            "modified": 1661005352376,
            "created": 1661005352376,
            "name": "Social Network",
            "description": "",
            "scope": "collection",
            "_type": "workspace"
        },
        {
            "_id": "req_f69e70fb70cb4437a97ca12fb8eb13dd",
            "parentId": "fld_d8262520aa2c424c899c7812a4b0f195",
            "modified": 1661008797283,
            "created": 1661005922021,
            "url": "http://localhost:3001/api/users",
            "name": "Fetch all users",
            "description": "",
            "method": "GET",
            "body": {},
            "parameters": [],
            "headers": [],
            "authentication": {},
            "metaSortKey": -1660382707469.5,
            "isPrivate": false,
            "settingStoreCookies": true,
            "settingSendCookies": true,
            "settingDisableRenderRequestBody": false,
            "settingEncodeUrl": true,
            "settingRebuildPath": true,
            "settingFollowRedirects": "global",
            "_type": "request"
        },
        {
            "_id": "fld_d8262520aa2c424c899c7812a4b0f195",
            "parentId": "wrk_a2af50c119e7496c87eff35e49c5520b",
            "modified": 1661008774626,
            "created": 1661008774626,
            "name": "Users",
            "description": "",
            "environment": {},
            "environmentPropertyOrder": null,
            "metaSortKey": -1661008774626,
            "_type": "request_group"
        },
        {
            "_id": "req_7725bd8e6d4b4f7aba3c4cb8cc66a6f5",
            "parentId": "fld_d8262520aa2c424c899c7812a4b0f195",
            "modified": 1661009786244,
            "created": 1661008770997,
            "url": "http://localhost:3001/api/users/6300fa644549589ca5bdadd9",
            "name": "Fetch single user",
            "description": "",
            "method": "GET",
            "body": {},
            "parameters": [],
            "headers": [],
            "authentication": {},
            "metaSortKey": -1660382707419.5,
            "isPrivate": false,
            "settingStoreCookies": true,
            "settingSendCookies": true,
            "settingDisableRenderRequestBody": false,
            "settingEncodeUrl": true,
            "settingRebuildPath": true,
            "settingFollowRedirects": "global",
            "_type": "request"
        },
        {
            "_id": "req_f237ba382bdd4aadaaadd953b8e9ba37",
            "parentId": "fld_d8262520aa2c424c899c7812a4b0f195",
            "modified": 1661010422249,
            "created": 1661007973425,
            "url": "http://localhost:3001/api/users",
            "name": "Create User",
            "description": "",
            "method": "POST",
            "body": {
                "mimeType": "application/json",
                "text": "{\n  \"username\": \"ironman\",\n  \"email\": \"iron@man.com\"\n}\n"
            },
            "parameters": [],
            "headers": [
                {
                    "name": "Content-Type",
                    "value": "application/json",
                    "id": "pair_a2e5b4c8be6b422585fc44365ef9a88f"
                }
            ],
            "authentication": {},
            "metaSortKey": -1660382707369.5,
            "isPrivate": false,
            "settingStoreCookies": true,
            "settingSendCookies": true,
            "settingDisableRenderRequestBody": false,
            "settingEncodeUrl": true,
            "settingRebuildPath": true,
            "settingFollowRedirects": "global",
            "_type": "request"
        },
        {
            "_id": "req_fcd06150f2cc460ebee4874a742a88a5",
            "parentId": "fld_d8262520aa2c424c899c7812a4b0f195",
            "modified": 1661010774773,
            "created": 1661010093064,
            "url": "http://localhost:3001/api/users/6300fa644549589ca5bdadd9",
            "name": "Update User",
            "description": "",
            "method": "PUT",
            "body": {
                "mimeType": "application/json",
                "text": "{\n  \"username\": \"tonystark3\",\n  \"email\": \"tony@stark.com\"\n}\n"
            },
            "parameters": [],
            "headers": [
                {
                    "name": "Content-Type",
                    "value": "application/json",
                    "id": "pair_a2e5b4c8be6b422585fc44365ef9a88f"
                }
            ],
            "authentication": {},
            "metaSortKey": -1660330820077.125,
            "isPrivate": false,
            "settingStoreCookies": true,
            "settingSendCookies": true,
            "settingDisableRenderRequestBody": false,
            "settingEncodeUrl": true,
            "settingRebuildPath": true,
            "settingFollowRedirects": "global",
            "_type": "request"
        },
        {
            "_id": "req_5d45213bfe0540c88818d80a720d81d0",
            "parentId": "fld_d8262520aa2c424c899c7812a4b0f195",
            "modified": 1661009362594,
            "created": 1661009347200,
            "url": "http://localhost:3001/api/users/6300fbbdb18070f538671cb8",
            "name": "Delete User",
            "description": "",
            "method": "DELETE",
            "body": {},
            "parameters": [],
            "headers": [],
            "authentication": {},
            "metaSortKey": -1660278932784.75,
            "isPrivate": false,
            "settingStoreCookies": true,
            "settingSendCookies": true,
            "settingDisableRenderRequestBody": false,
            "settingEncodeUrl": true,
            "settingRebuildPath": true,
            "settingFollowRedirects": "global",
            "_type": "request"
        },
        {
            "_id": "env_b35da1fc21cb6589762b14751c25f0227069c4a1",
            "parentId": "wrk_a2af50c119e7496c87eff35e49c5520b",
            "modified": 1661005352380,
            "created": 1661005352380,
            "name": "Base Environment",
            "data": {},
            "dataPropertyOrder": null,
            "color": null,
            "isPrivate": false,
            "metaSortKey": 1661005352380,
            "_type": "environment"
        },
        {
            "_id": "jar_b35da1fc21cb6589762b14751c25f0227069c4a1",
            "parentId": "wrk_a2af50c119e7496c87eff35e49c5520b",
            "modified": 1661005352381,
            "created": 1661005352381,
            "name": "Default Jar",
            "cookies": [],
            "_type": "cookie_jar"
        },
        {
            "_id": "spc_77ee88707bd54f8babeeffbc416f3642",
            "parentId": "wrk_a2af50c119e7496c87eff35e49c5520b",
            "modified": 1661005352378,
            "created": 1661005352378,
            "fileName": "Social Network",
            "contents": "",
            "contentType": "yaml",
            "_type": "api_spec"
        }
    ]
}